my_visualization_lib/__init__.py
my_visualization_lib/factory.py
my_visualization_lib/filter.py
my_visualization_lib/loader.py
my_visualization_lib/visualizer.py
my_visualization_lib-1.0.dist-info/LICENSE
my_visualization_lib-1.0.dist-info/METADATA
my_visualization_lib-1.0.dist-info/WHEEL
my_visualization_lib-1.0.dist-info/top_level.txt
my_visualization_lib-1.0.dist-info/RECORD
